printado/__init__.py
printado/config.py
printado/hotkey_listener.py
printado/main.py
printado/version.py
printado/core/__init__.py
printado/core/blur_background.py
printado/core/event_handler.py
printado/core/screenshot_editor.py
printado/core/screenshot_manager.py
printado/core/selection_window.py
printado/core/theme.py
printado/core/tool_manager.py
printado/core/toolbar.py
printado/core/utils.py
printado/modules/__init__.py
printado/modules/gui.py
printado/modules/text_format.py
printado/modules/update_checker.py
printado/modules/upload.py
printado/modules/upload_dialog.py
printado-1.0.1.dist-info/LICENSE
printado-1.0.1.dist-info/METADATA
printado-1.0.1.dist-info/WHEEL
printado-1.0.1.dist-info/entry_points.txt
printado-1.0.1.dist-info/top_level.txt
printado-1.0.1.dist-info/RECORD
